README
setup.py
geoleaflet/__init__.py
geoleaflet/geoleaflet.py
geoleaflet.egg-info/PKG-INFO
geoleaflet.egg-info/SOURCES.txt
geoleaflet.egg-info/dependency_links.txt
geoleaflet.egg-info/requires.txt
geoleaflet.egg-info/top_level.txt